webcrypt/__init__.py
webcrypt/convert.py
webcrypt/exceptions.py
webcrypt/jose.py
webcrypt/jwe.py
webcrypt/jws.py
webcrypt/keys.py
webcrypt/py.typed
webcrypt/rfc1751.py
webcrypt-1.5.0.dist-info/LICENSE
webcrypt-1.5.0.dist-info/METADATA
webcrypt-1.5.0.dist-info/WHEEL
webcrypt-1.5.0.dist-info/entry_points.txt
webcrypt-1.5.0.dist-info/RECORD
