Metadata-Version: 2.3
Name: webcrypt
Version: 1.5.0
Summary: High level Constructs for Web App cryptography and JOSE spec implementation
License: Apache-2.0
Keywords: cryptography,security,OpenID,OAuth2,JWT,JOSE,JWE,JWS,JWK,WebCryptography
Author: mk
Author-email: mk@plataux.com
Requires-Python: >3.9.1,<4
Classifier: License :: OSI Approved :: Apache Software License
Classifier: Operating System :: OS Independent
Classifier: Programming Language :: Python :: 3
Classifier: Programming Language :: Python :: 3.10
Classifier: Programming Language :: Python :: 3.11
Classifier: Programming Language :: Python :: 3.12
Classifier: Programming Language :: Python :: 3.13
Classifier: Topic :: Software Development :: Build Tools
Classifier: Topic :: Software Development :: Libraries :: Python Modules
Requires-Dist: cryptography (>=45,<46)
Requires-Dist: pydantic (>=2,<3)
Project-URL: Homepage, https://github.com/plataux/webcrypt
Project-URL: Repository, https://github.com/plataux/webcrypt
